{"bitvecsize": 8, "symbols_1": {"I": 246, "J": 207, "K": 192, "L": 170}, "symbols_2": {"I": 251, "J": 255, "K": 227, "L": 116}, "regact_id": {"I": 2, "J": 0, "K": 3, "L": 1}, "states_1": {"-1_0": 251, "0_0": 0, "1_0": 249, "2_0": 57, "3_0": 8, "4_0": 107, "5_0": 58, "6_0": 9, "7_0": 233, "8_0": 38, "9_0": 99, "10_0": 50, "11_0": 11, "12_0": 187, "13_0": 248, "14_0": 56, "15_0": 7, "16_0": 255}, "states_2": {"-1_0": 251, "0_0": 208, "1_0": 251, "2_0": 251, "3_0": 242, "4_0": 251, "5_0": 242, "6_0": 233, "7_0": 251, "8_0": 91, "9_0": 91, "10_0": 82, "11_0": 155, "12_0": 251, "13_0": 91, "14_0": 251, "15_0": 242, "16_0": 255}, "regacts": [{"logic_ops": ["or"], "preds": [{"op": "eq", "const": 4, "sym_opt": "const", "state_opt": "s2"}, {"op": "le", "const": 74, "sym_opt": "s2", "state_opt": "s1"}], "ariths": [{"op": "plus", "sym_const": 255, "sym_opt": "s1", "state_opt": "s1", "state_const": 180}, {"op": "plus", "sym_const": 247, "sym_opt": "const", "state_opt": "s2", "state_const": 250}, {"op": "or", "sym_const": 187, "sym_opt": "const", "state_opt": "s2", "state_const": 161}, {"op": "or", "sym_const": 251, "sym_opt": "const", "state_opt": "s2", "state_const": 32}]}, {"logic_ops": ["and"], "preds": [{"op": "neq", "const": 102, "sym_opt": "s2", "state_opt": "s1"}, {"op": "ge", "const": 103, "sym_opt": "s1", "state_opt": "s1"}], "ariths": [{"op": "or", "sym_const": 251, "sym_opt": "const", "state_opt": "s1", "state_const": 239}, {"op": "or", "sym_const": 251, "sym_opt": "const", "state_opt": "s1", "state_const": 213}, {"op": "subr", "sym_const": 195, "sym_opt": "const", "state_opt": "s1", "state_const": 240}, {"op": "and", "sym_const": 95, "sym_opt": "const", "state_opt": "s2", "state_const": 118}]}, {"logic_ops": ["and"], "preds": [{"op": "neq", "const": 2, "sym_opt": "s1", "state_opt": "s1"}, {"op": "neq", "const": 206, "sym_opt": "const", "state_opt": "s1"}], "ariths": [{"op": "or", "sym_const": 72, "sym_opt": "s2", "state_opt": "s2", "state_const": 102}, {"op": "or", "sym_const": 22, "sym_opt": "s2", "state_opt": "s2", "state_const": 31}, {"op": "sub", "sym_const": 93, "sym_opt": "const", "state_opt": "s2", "state_const": 96}, {"op": "sub", "sym_const": 237, "sym_opt": "const", "state_opt": "s2", "state_const": 216}]}, {"logic_ops": ["or"], "preds": [{"op": "ge", "const": 69, "sym_opt": "s1", "state_opt": "s1"}, {"op": "eq", "const": 52, "sym_opt": "s2", "state_opt": "s1"}], "ariths": [{"op": "or", "sym_const": 233, "sym_opt": "const", "state_opt": "s2", "state_const": 2}, {"op": "or", "sym_const": 251, "sym_opt": "const", "state_opt": "s2", "state_const": 131}, {"op": "subr", "sym_const": 215, "sym_opt": "s1", "state_opt": "s1", "state_const": 91}, {"op": "or", "sym_const": 107, "sym_opt": "s2", "state_opt": "s2", "state_const": 51}]}]}