{"bitvecsize": 8, "symbols_1": {"K": 7, "L": 216, "M": 80, "N": 20, "O": 232}, "symbols_2": {"K": 115, "L": 253, "M": 30, "N": 0, "O": 148}, "regact_id": {"K": 3, "L": 0, "M": 1, "N": 0, "O": 3}, "states_1": {"-1_0": 16, "0_0": 0, "1_0": 24, "2_0": 247, "3_0": 216, "4_0": 20, "5_0": 152, "6_0": 158, "7_0": 19, "8_0": 64}, "states_2": {"-1_0": 16, "0_0": 27, "1_0": 16, "2_0": 16, "3_0": 20, "4_0": 152, "5_0": 155, "6_0": 16, "7_0": 16, "8_0": 64}, "regacts": [{"logic_ops": ["and", "or"], "preds": [{"op": "neq", "const": 20, "sym_opt": "s1", "state_opt": "s1"}, {"op": "le", "const": 86, "sym_opt": "s1", "state_opt": "s1"}], "ariths": [{"op": "subr", "sym_const": 113, "sym_opt": "s2", "state_opt": "s2", "state_const": 144}, {"op": "and", "sym_const": 80, "sym_opt": "const", "state_opt": "s2", "state_const": 210}, {"op": "and", "sym_const": 223, "sym_opt": "s1", "state_opt": "s2", "state_const": 105}, {"op": "subr", "sym_const": 65, "sym_opt": "s2", "state_opt": "const", "state_const": 152}]}, {"logic_ops": ["left", "right"], "preds": [{"op": "eq", "const": 207, "sym_opt": "s2", "state_opt": "s1"}, {"op": "neq", "const": 237, "sym_opt": "const", "state_opt": "s1"}], "ariths": [{"op": "sub", "sym_const": 83, "sym_opt": "const", "state_opt": "s1", "state_const": 242}, {"op": "and", "sym_const": 235, "sym_opt": "s1", "state_opt": "s2", "state_const": 0}, {"op": "and", "sym_const": 144, "sym_opt": "s1", "state_opt": "s2", "state_const": 128}, {"op": "and", "sym_const": 232, "sym_opt": "const", "state_opt": "const", "state_const": 85}]}, {"logic_ops": ["and", "left"], "preds": [{"op": "ge", "const": 218, "sym_opt": "s2", "state_opt": "s1"}, {"op": "neq", "const": 226, "sym_opt": "s2", "state_opt": "s1"}], "ariths": [{"op": "xor", "sym_const": 94, "sym_opt": "s2", "state_opt": "const", "state_const": 146}, {"op": "subr", "sym_const": 123, "sym_opt": "const", "state_opt": "s1", "state_const": 204}, {"op": "sub", "sym_const": 115, "sym_opt": "const", "state_opt": "s2", "state_const": 235}, {"op": "and", "sym_const": 198, "sym_opt": "const", "state_opt": "const", "state_const": 27}]}, {"logic_ops": ["left", "or"], "preds": [{"op": "eq", "const": 117, "sym_opt": "s2", "state_opt": "s1"}, {"op": "eq", "const": 236, "sym_opt": "const", "state_opt": "s2"}], "ariths": [{"op": "sub", "sym_const": 141, "sym_opt": "s1", "state_opt": "s2", "state_const": 55}, {"op": "and", "sym_const": 20, "sym_opt": "const", "state_opt": "s1", "state_const": 21}, {"op": "and", "sym_const": 80, "sym_opt": "const", "state_opt": "s2", "state_const": 18}, {"op": "and", "sym_const": 116, "sym_opt": "const", "state_opt": "s2", "state_const": 49}]}]}