{"bitvecsize": 8, "symbols_1": {"E": 103, "F": 185, "H": 163, "K": 236, "L": 9}, "symbols_2": {"E": 26, "F": 248, "H": 168, "K": 192, "L": 149}, "regact_id": {"E": 1, "F": 1, "H": 3, "K": 2, "L": 2}, "states_1": {"-1_0": 171, "0_0": 0, "1_0": 170, "2_0": 34, "3_0": 10, "4_0": 2, "5_0": 161, "6_0": 136, "7_0": 168, "8_0": 251}, "states_2": {"-1_0": 169, "0_0": 95, "1_0": 202, "2_0": 10, "3_0": 99, "4_0": 169, "5_0": 141, "6_0": 169, "7_0": 169, "8_0": 169}, "regacts": [{"logic_ops": ["and", "left"], "preds": [{"op": "eq", "const": 107, "sym_opt": "s1", "state_opt": "s2"}, {"op": "neq", "const": 85, "sym_opt": "const", "state_opt": "s1"}], "ariths": [{"op": "plus", "sym_const": 49, "sym_opt": "const", "state_opt": "const", "state_const": 41}, {"op": "xor", "sym_const": 149, "sym_opt": "const", "state_opt": "const", "state_const": 89}, {"op": "plus", "sym_const": 206, "sym_opt": "const", "state_opt": "const", "state_const": 39}, {"op": "subr", "sym_const": 175, "sym_opt": "const", "state_opt": "s2", "state_const": 142}]}, {"logic_ops": ["left", "right"], "preds": [{"op": "le", "const": 226, "sym_opt": "s2", "state_opt": "s1"}, {"op": "ge", "const": 135, "sym_opt": "s2", "state_opt": "s2"}], "ariths": [{"op": "or", "sym_const": 171, "sym_opt": "const", "state_opt": "s1", "state_const": 25}, {"op": "sub", "sym_const": 186, "sym_opt": "const", "state_opt": "const", "state_const": 17}, {"op": "and", "sym_const": 54, "sym_opt": "s2", "state_opt": "s2", "state_const": 57}, {"op": "and", "sym_const": 55, "sym_opt": "s1", "state_opt": "const", "state_const": 235}]}, {"logic_ops": ["or", "or"], "preds": [{"op": "le", "const": 137, "sym_opt": "s2", "state_opt": "s2"}, {"op": "ge", "const": 52, "sym_opt": "s1", "state_opt": "s2"}], "ariths": [{"op": "or", "sym_const": 171, "sym_opt": "const", "state_opt": "s1", "state_const": 252}, {"op": "subr", "sym_const": 31, "sym_opt": "const", "state_opt": "const", "state_const": 200}, {"op": "sub", "sym_const": 238, "sym_opt": "s1", "state_opt": "s2", "state_const": 138}, {"op": "xor", "sym_const": 66, "sym_opt": "s2", "state_opt": "s2", "state_const": 65}]}, {"logic_ops": ["or", "left"], "preds": [{"op": "eq", "const": 91, "sym_opt": "s1", "state_opt": "s1"}, {"op": "eq", "const": 88, "sym_opt": "const", "state_opt": "s1"}], "ariths": [{"op": "sub", "sym_const": 163, "sym_opt": "const", "state_opt": "s1", "state_const": 225}, {"op": "plus", "sym_const": 66, "sym_opt": "s1", "state_opt": "const", "state_const": 234}, {"op": "or", "sym_const": 171, "sym_opt": "const", "state_opt": "s1", "state_const": 187}, {"op": "subr", "sym_const": 105, "sym_opt": "s2", "state_opt": "const", "state_const": 81}]}]}