{"bitvecsize": 8, "symbols_1": {"I": 87, "J": 89, "K": 78}, "symbols_2": {"I": 115, "J": 2, "K": 37}, "regact_id": {"I": 2, "J": 1, "K": 0}, "states_1": {"-1_0": 118, "0_0": 0, "1_0": 122, "2_0": 238, "3_0": 124, "4_0": 6, "5_0": 116, "6_0": 112, "7_0": 246, "8_0": 248}, "states_2": {"-1_0": 118, "0_0": 116, "1_0": 238, "2_0": 114, "3_0": 0, "4_0": 114, "5_0": 118, "6_0": 246, "7_0": 246, "8_0": 246}, "regacts": [{"logic_ops": ["or", "or"], "preds": [{"op": "eq", "const": 229, "sym_opt": "s2", "state_opt": "s1"}, {"op": "le", "const": 49, "sym_opt": "s1", "state_opt": "s1"}], "ariths": [{"op": "subr", "sym_const": 110, "sym_opt": "s1", "state_opt": "const", "state_const": 196}, {"op": "xor", "sym_const": 118, "sym_opt": "const", "state_opt": "const", "state_const": 0}, {"op": "sub", "sym_const": 238, "sym_opt": "const", "state_opt": "s2", "state_const": 189}, {"op": "sub", "sym_const": 238, "sym_opt": "const", "state_opt": "s1", "state_const": 167}]}, {"logic_ops": ["and", "or"], "preds": [{"op": "le", "const": 118, "sym_opt": "s1", "state_opt": "s1"}, {"op": "le", "const": 136, "sym_opt": "s2", "state_opt": "s1"}], "ariths": [{"op": "plus", "sym_const": 114, "sym_opt": "s2", "state_opt": "s2", "state_const": 49}, {"op": "or", "sym_const": 22, "sym_opt": "const", "state_opt": "s2", "state_const": 28}, {"op": "or", "sym_const": 6, "sym_opt": "const", "state_opt": "s2", "state_const": 88}, {"op": "plus", "sym_const": 252, "sym_opt": "const", "state_opt": "const", "state_const": 118}]}, {"logic_ops": ["or", "or"], "preds": [{"op": "eq", "const": 25, "sym_opt": "s2", "state_opt": "s1"}, {"op": "eq", "const": 149, "sym_opt": "s2", "state_opt": "s1"}], "ariths": [{"op": "and", "sym_const": 250, "sym_opt": "const", "state_opt": "s1", "state_const": 120}, {"op": "xor", "sym_const": 155, "sym_opt": "const", "state_opt": "const", "state_const": 109}, {"op": "sub", "sym_const": 236, "sym_opt": "const", "state_opt": "const", "state_const": 118}, {"op": "xor", "sym_const": 217, "sym_opt": "const", "state_opt": "const", "state_const": 175}]}, {"logic_ops": ["or", "right"], "preds": [{"op": "le", "const": 8, "sym_opt": "const", "state_opt": "const"}, {"op": "ge", "const": 181, "sym_opt": "s1", "state_opt": "s2"}], "ariths": [{"op": "plus", "sym_const": 51, "sym_opt": "s1", "state_opt": "const", "state_const": 31}, {"op": "sub", "sym_const": 118, "sym_opt": "const", "state_opt": "const", "state_const": 79}, {"op": "sub", "sym_const": 250, "sym_opt": "const", "state_opt": "const", "state_const": 248}, {"op": "and", "sym_const": 194, "sym_opt": "const", "state_opt": "const", "state_const": 139}]}]}