{"bitvecsize": 8, "symbols_1": {"D": 223, "E": 31, "F": 152, "G": 140}, "symbols_2": {"D": 240, "E": 127, "F": 160, "G": 226}, "regact_id": {"D": 0, "E": 1, "F": 0, "G": 0}, "states_1": {"-1_0": 32, "0_0": 0, "1_0": 12, "2_0": 121, "3_0": 71, "4_0": 185, "5_0": 65, "6_0": 57, "7_0": 171, "8_0": 129}, "states_2": {"-1_0": 0, "0_0": 117, "1_0": 8, "2_0": 198, "3_0": 56, "4_0": 64, "5_0": 184, "6_0": 42, "7_0": 0, "8_0": 0}, "regacts": [{"logic_ops": ["and", "right"], "preds": [{"op": "neq", "const": 127, "sym_opt": "const", "state_opt": "s1"}, {"op": "neq", "const": 104, "sym_opt": "s1", "state_opt": "s1"}], "ariths": [{"op": "subr", "sym_const": 58, "sym_opt": "const", "state_opt": "const", "state_const": 90}, {"op": "sub", "sym_const": 106, "sym_opt": "const", "state_opt": "const", "state_const": 106}, {"op": "sub", "sym_const": 129, "sym_opt": "const", "state_opt": "s2", "state_const": 123}, {"op": "subr", "sym_const": 224, "sym_opt": "s2", "state_opt": "const", "state_const": 168}]}, {"logic_ops": ["left", "right"], "preds": [{"op": "le", "const": 85, "sym_opt": "const", "state_opt": "s1"}, {"op": "le", "const": 4, "sym_opt": "s2", "state_opt": "s2"}], "ariths": [{"op": "subr", "sym_const": 37, "sym_opt": "s2", "state_opt": "s2", "state_const": 117}, {"op": "and", "sym_const": 64, "sym_opt": "const", "state_opt": "s1", "state_const": 116}, {"op": "sub", "sym_const": 19, "sym_opt": "const", "state_opt": "const", "state_const": 243}, {"op": "subr", "sym_const": 142, "sym_opt": "const", "state_opt": "s2", "state_const": 0}]}, {"logic_ops": ["and", "and"], "preds": [{"op": "ge", "const": 124, "sym_opt": "s1", "state_opt": "const"}, {"op": "le", "const": 81, "sym_opt": "s2", "state_opt": "s2"}], "ariths": [{"op": "subr", "sym_const": 122, "sym_opt": "s1", "state_opt": "s2", "state_const": 252}, {"op": "sub", "sym_const": 65, "sym_opt": "const", "state_opt": "const", "state_const": 123}, {"op": "and", "sym_const": 142, "sym_opt": "s2", "state_opt": "s2", "state_const": 120}, {"op": "and", "sym_const": 1, "sym_opt": "s2", "state_opt": "s1", "state_const": 104}]}, {"logic_ops": ["or", "right"], "preds": [{"op": "ge", "const": 0, "sym_opt": "const", "state_opt": "const"}, {"op": "ge", "const": 1, "sym_opt": "const", "state_opt": "const"}], "ariths": [{"op": "or", "sym_const": 180, "sym_opt": "const", "state_opt": "s2", "state_const": 11}, {"op": "xor", "sym_const": 121, "sym_opt": "const", "state_opt": "const", "state_const": 248}, {"op": "xor", "sym_const": 63, "sym_opt": "const", "state_opt": "s2", "state_const": 33}, {"op": "or", "sym_const": 25, "sym_opt": "const", "state_opt": "const", "state_const": 40}]}]}