{"bitvecsize": 8, "symbols_1": {"F": 134, "I": 0, "J": 41}, "symbols_2": {"F": 229, "I": 219, "J": 218}, "regact_id": {"F": 2, "I": 0, "J": 3}, "states_1": {"rej_0": 219, "accFIJI_0": 251, "accJJII_0": 255, "p_0": 0, "pF_0": 139, "pJ_0": 218, "pFI_0": 137, "pJJ_0": 3, "pJJI_0": 1, "pFIJ_0": 178}, "regacts": [{"logic_ops": ["and"], "preds": [{"op": "neq", "const": 154, "sym_opt": "s2", "state_opt": "s1"}, {"op": "le", "const": 0, "sym_opt": "s1", "state_opt": "s1"}], "ariths": [{"op": "or", "sym_const": 119, "sym_opt": "s2", "state_opt": "s1", "state_const": 32}, {"op": "plus", "sym_const": 254, "sym_opt": "const", "state_opt": "s1", "state_const": 28}]}, {"logic_ops": ["or"], "preds": [{"op": "eq", "const": 241, "sym_opt": "s1", "state_opt": "const"}, {"op": "neq", "const": 220, "sym_opt": "s2", "state_opt": "s1"}], "ariths": [{"op": "or", "sym_const": 101, "sym_opt": "const", "state_opt": "s1", "state_const": 43}, {"op": "subr", "sym_const": 44, "sym_opt": "const", "state_opt": "const", "state_const": 146}]}, {"logic_ops": ["and"], "preds": [{"op": "le", "const": 122, "sym_opt": "s1", "state_opt": "s1"}, {"op": "le", "const": 38, "sym_opt": "s1", "state_opt": "s1"}], "ariths": [{"op": "or", "sym_const": 139, "sym_opt": "const", "state_opt": "s1", "state_const": 10}, {"op": "subr", "sym_const": 183, "sym_opt": "const", "state_opt": "const", "state_const": 146}]}, {"logic_ops": ["or"], "preds": [{"op": "le", "const": 124, "sym_opt": "s1", "state_opt": "s1"}, {"op": "eq", "const": 117, "sym_opt": "const", "state_opt": "s1"}], "ariths": [{"op": "or", "sym_const": 152, "sym_opt": "s2", "state_opt": "s1", "state_const": 8}, {"op": "plus", "sym_const": 168, "sym_opt": "s1", "state_opt": "s1", "state_const": 0}]}]}