{"bitvecsize": 8, "symbols_1": {"K": 210, "L": 188, "M": 69}, "symbols_2": {"K": 2, "L": 238, "M": 126}, "regact_id": {"K": 0, "L": 1, "M": 3}, "states_1": {"-1_0": 82, "0_0": 0, "1_0": 141, "2_0": 23, "3_0": 240, "4_0": 114, "5_0": 50, "6_0": 85, "7_0": 79, "8_0": 56, "9_0": 24, "10_0": 60, "11_0": 242, "12_0": 210}, "states_2": {"-1_0": 150, "0_0": 81, "1_0": 150, "2_0": 180, "3_0": 54, "4_0": 150, "5_0": 153, "6_0": 150, "7_0": 124, "8_0": 150, "9_0": 0, "10_0": 54, "11_0": 150, "12_0": 150}, "regacts": [{"logic_ops": ["and", "right"], "preds": [{"op": "neq", "const": 44, "sym_opt": "s2", "state_opt": "s1"}, {"op": "neq", "const": 198, "sym_opt": "s2", "state_opt": "s1"}], "ariths": [{"op": "plus", "sym_const": 65, "sym_opt": "const", "state_opt": "const", "state_const": 17}, {"op": "plus", "sym_const": 34, "sym_opt": "s1", "state_opt": "const", "state_const": 196}, {"op": "and", "sym_const": 222, "sym_opt": "const", "state_opt": "s1", "state_const": 10}, {"op": "and", "sym_const": 4, "sym_opt": "const", "state_opt": "const", "state_const": 89}]}, {"logic_ops": ["right", "and"], "preds": [{"op": "le", "const": 134, "sym_opt": "s2", "state_opt": "s1"}, {"op": "le", "const": 225, "sym_opt": "s2", "state_opt": "s1"}], "ariths": [{"op": "subr", "sym_const": 196, "sym_opt": "const", "state_opt": "s2", "state_const": 0}, {"op": "xor", "sym_const": 90, "sym_opt": "const", "state_opt": "const", "state_const": 108}, {"op": "plus", "sym_const": 101, "sym_opt": "s1", "state_opt": "s2", "state_const": 186}, {"op": "and", "sym_const": 158, "sym_opt": "const", "state_opt": "const", "state_const": 151}]}, {"logic_ops": ["and", "left"], "preds": [{"op": "eq", "const": 106, "sym_opt": "const", "state_opt": "s2"}, {"op": "neq", "const": 188, "sym_opt": "s1", "state_opt": "s1"}], "ariths": [{"op": "or", "sym_const": 78, "sym_opt": "s1", "state_opt": "const", "state_const": 2}, {"op": "and", "sym_const": 35, "sym_opt": "const", "state_opt": "s1", "state_const": 218}, {"op": "sub", "sym_const": 13, "sym_opt": "s1", "state_opt": "const", "state_const": 136}, {"op": "subr", "sym_const": 98, "sym_opt": "const", "state_opt": "const", "state_const": 104}]}, {"logic_ops": ["left", "and"], "preds": [{"op": "ge", "const": 45, "sym_opt": "s2", "state_opt": "s1"}, {"op": "ge", "const": 192, "sym_opt": "const", "state_opt": "s1"}], "ariths": [{"op": "sub", "sym_const": 164, "sym_opt": "const", "state_opt": "s1", "state_const": 6}, {"op": "subr", "sym_const": 217, "sym_opt": "const", "state_opt": "s1", "state_const": 218}, {"op": "sub", "sym_const": 166, "sym_opt": "const", "state_opt": "const", "state_const": 84}, {"op": "subr", "sym_const": 135, "sym_opt": "const", "state_opt": "const", "state_const": 29}]}]}