{"bitvecsize": 8, "symbols_1": {"D": 118, "E": 135, "F": 225, "G": 165}, "symbols_2": {"D": 166, "E": 181, "F": 45, "G": 105}, "regact_id": {"D": 2, "E": 1, "F": 0, "G": 0}, "states_1": {"-1_0": 223, "0_0": 0, "1_0": 222, "2_0": 143, "3_0": 203, "4_0": 7, "5_0": 5, "6_0": 3, "7_0": 1, "8_0": 255}, "regacts": [{"logic_ops": ["left"], "preds": [{"op": "neq", "const": 144, "sym_opt": "s1", "state_opt": "s1"}], "ariths": [{"op": "or", "sym_const": 223, "sym_opt": "const", "state_opt": "s1", "state_const": 33}, {"op": "plus", "sym_const": 40, "sym_opt": "s2", "state_opt": "const", "state_const": 158}]}, {"logic_ops": ["left"], "preds": [{"op": "ge", "const": 255, "sym_opt": "const", "state_opt": "s1"}], "ariths": [{"op": "subr", "sym_const": 2, "sym_opt": "const", "state_opt": "s1", "state_const": 132}, {"op": "or", "sym_const": 223, "sym_opt": "const", "state_opt": "s1", "state_const": 161}]}, {"logic_ops": ["left"], "preds": [{"op": "eq", "const": 172, "sym_opt": "s1", "state_opt": "s1"}], "ariths": [{"op": "sub", "sym_const": 192, "sym_opt": "s2", "state_opt": "const", "state_const": 23}, {"op": "or", "sym_const": 222, "sym_opt": "const", "state_opt": "s1", "state_const": 131}]}]}