{"bitvecsize": 8, "symbols_1": {"D": 204, "E": 196, "F": 134, "G": 109}, "symbols_2": {"D": 39, "E": 91, "F": 250, "G": 193}, "regact_id": {"D": 1, "E": 1, "F": 3, "G": 2}, "states_1": {"-1_0": 220, "0_0": 0, "1_0": 204, "2_0": 144, "3_0": 200, "4_0": 8, "5_0": 72, "6_0": 136, "7_0": 76, "8_0": 140, "9_0": 196, "10_0": 252}, "regacts": [{"logic_ops": ["and"], "preds": [{"op": "neq", "const": 4, "sym_opt": "const", "state_opt": "s1"}, {"op": "ge", "const": 86, "sym_opt": "s2", "state_opt": "s1"}], "ariths": [{"op": "subr", "sym_const": 24, "sym_opt": "const", "state_opt": "const", "state_const": 222}, {"op": "subr", "sym_const": 47, "sym_opt": "const", "state_opt": "s1", "state_const": 99}]}, {"logic_ops": ["and"], "preds": [{"op": "neq", "const": 217, "sym_opt": "s2", "state_opt": "s1"}, {"op": "neq", "const": 180, "sym_opt": "s1", "state_opt": "s1"}], "ariths": [{"op": "or", "sym_const": 220, "sym_opt": "const", "state_opt": "s1", "state_const": 226}, {"op": "plus", "sym_const": 110, "sym_opt": "s1", "state_opt": "s1", "state_const": 82}]}, {"logic_ops": ["and"], "preds": [{"op": "le", "const": 207, "sym_opt": "s1", "state_opt": "s1"}, {"op": "le", "const": 54, "sym_opt": "s2", "state_opt": "s1"}], "ariths": [{"op": "plus", "sym_const": 56, "sym_opt": "const", "state_opt": "s1", "state_const": 181}, {"op": "or", "sym_const": 220, "sym_opt": "const", "state_opt": "s1", "state_const": 0}]}, {"logic_ops": ["or"], "preds": [{"op": "le", "const": 243, "sym_opt": "s1", "state_opt": "s1"}, {"op": "eq", "const": 62, "sym_opt": "s2", "state_opt": "s1"}], "ariths": [{"op": "plus", "sym_const": 64, "sym_opt": "const", "state_opt": "s1", "state_const": 203}, {"op": "or", "sym_const": 220, "sym_opt": "const", "state_opt": "s1", "state_const": 154}]}]}