{"bitvecsize": 8, "symbols_1": {"A": 6, "G": 125, "H": 247, "J": 118, "L": 66, "M": 87, "N": 142}, "symbols_2": {"A": 196, "G": 68, "H": 204, "J": 201, "L": 202, "M": 106, "N": 135}, "regact_id": {"A": 0, "G": 1, "H": 3, "J": 0, "L": 0, "M": 2, "N": 0}, "states_1": {"rej_0": 119, "accLMMM_0": 221, "accHJHG_0": 253, "accALMN_0": 255, "p_0": 0, "pL_0": 202, "pA_0": 196, "pH_0": 204, "pLM_0": 52, "pHJ_0": 5, "pAL_0": 14, "pLMM_0": 115, "pHJH_0": 205, "pALM_0": 120}, "states_2": {"rej_0": 119, "accLMMM_0": 220, "accHJHG_0": 253, "accALMN_0": 255, "p_0": 119, "pL_0": 115, "pA_0": 119, "pH_0": 119, "pLM_0": 51, "pHJ_0": 119, "pAL_0": 115, "pLMM_0": 51, "pHJH_0": 119, "pALM_0": 119}, "regacts": [{"logic_ops": ["or"], "preds": [{"op": "eq", "const": 250, "sym_opt": "s1", "state_opt": "s1"}, {"op": "eq", "const": 190, "sym_opt": "s1", "state_opt": "s1"}], "ariths": [{"op": "xor", "sym_const": 0, "sym_opt": "s2", "state_opt": "s1", "state_const": 23}, {"op": "or", "sym_const": 0, "sym_opt": "s1", "state_opt": "const", "state_const": 113}, {"op": "or", "sym_const": 69, "sym_opt": "const", "state_opt": "s2", "state_const": 81}, {"op": "or", "sym_const": 84, "sym_opt": "const", "state_opt": "s2", "state_const": 255}]}, {"logic_ops": ["and"], "preds": [{"op": "neq", "const": 182, "sym_opt": "s1", "state_opt": "s1"}, {"op": "le", "const": 156, "sym_opt": "s2", "state_opt": "const"}], "ariths": [{"op": "or", "sym_const": 85, "sym_opt": "const", "state_opt": "s2", "state_const": 60}, {"op": "or", "sym_const": 96, "sym_opt": "s2", "state_opt": "s2", "state_const": 95}, {"op": "or", "sym_const": 120, "sym_opt": "const", "state_opt": "s1", "state_const": 48}, {"op": "sub", "sym_const": 202, "sym_opt": "const", "state_opt": "s1", "state_const": 159}]}, {"logic_ops": ["or"], "preds": [{"op": "eq", "const": 141, "sym_opt": "const", "state_opt": "s2"}, {"op": "eq", "const": 54, "sym_opt": "s1", "state_opt": "s1"}], "ariths": [{"op": "plus", "sym_const": 252, "sym_opt": "s2", "state_opt": "s1", "state_const": 67}, {"op": "subr", "sym_const": 151, "sym_opt": "const", "state_opt": "s1", "state_const": 218}, {"op": "or", "sym_const": 81, "sym_opt": "const", "state_opt": "s2", "state_const": 152}, {"op": "subr", "sym_const": 0, "sym_opt": "const", "state_opt": "s2", "state_const": 250}]}, {"logic_ops": ["or"], "preds": [{"op": "ge", "const": 165, "sym_opt": "const", "state_opt": "s1"}, {"op": "le", "const": 173, "sym_opt": "s2", "state_opt": "s1"}], "ariths": [{"op": "sub", "sym_const": 0, "sym_opt": "s1", "state_opt": "const", "state_const": 128}, {"op": "xor", "sym_const": 185, "sym_opt": "const", "state_opt": "const", "state_const": 206}, {"op": "or", "sym_const": 140, "sym_opt": "s2", "state_opt": "s1", "state_const": 60}, {"op": "and", "sym_const": 255, "sym_opt": "const", "state_opt": "s2", "state_const": 225}]}]}