{"bitvecsize": 8, "symbols_1": {"I": 129, "L": 253, "M": 250}, "symbols_2": {"I": 0, "L": 228, "M": 205}, "regact_id": {"I": 0, "L": 2, "M": 2}, "states_1": {"-1_0": 63, "0_0": 0, "1_0": 41, "2_0": 35, "3_0": 29, "4_0": 23, "5_0": 20, "6_0": 17, "7_0": 14, "8_0": 11, "9_0": 8, "10_0": 5, "11_0": 2, "12_0": 255}, "regacts": [{"logic_ops": ["left"], "preds": [{"op": "le", "const": 0, "sym_opt": "const", "state_opt": "s1"}, {"op": "neq", "const": 127, "sym_opt": "s1", "state_opt": "const"}], "ariths": [{"op": "or", "sym_const": 41, "sym_opt": "const", "state_opt": "s1", "state_const": 137}, {"op": "or", "sym_const": 56, "sym_opt": "const", "state_opt": "const", "state_const": 63}]}, {"logic_ops": ["left"], "preds": [{"op": "ge", "const": 35, "sym_opt": "s2", "state_opt": "s1"}, {"op": "ge", "const": 179, "sym_opt": "s2", "state_opt": "s1"}], "ariths": [{"op": "plus", "sym_const": 102, "sym_opt": "const", "state_opt": "s1", "state_const": 185}, {"op": "and", "sym_const": 191, "sym_opt": "const", "state_opt": "const", "state_const": 215}]}, {"logic_ops": ["or"], "preds": [{"op": "le", "const": 28, "sym_opt": "s2", "state_opt": "s1"}, {"op": "le", "const": 127, "sym_opt": "s2", "state_opt": "s1"}], "ariths": [{"op": "or", "sym_const": 63, "sym_opt": "const", "state_opt": "s1", "state_const": 220}, {"op": "plus", "sym_const": 79, "sym_opt": "s1", "state_opt": "s1", "state_const": 125}]}]}