{"bitvecsize": 8, "symbols_1": {"K": 253, "L": 200}, "symbols_2": {"K": 129, "L": 22}, "regact_id": {"K": 2, "L": 0}, "states_1": {"-1_0": 245, "0_0": 0, "1_0": 129, "2_0": 114, "3_0": 99, "4_0": 84, "5_0": 213, "6_0": 198, "7_0": 183, "8_0": 168, "9_0": 153, "10_0": 138, "11_0": 123, "12_0": 108, "13_0": 93, "14_0": 253}, "regacts": [{"logic_ops": ["left"], "preds": [{"op": "ge", "const": 12, "sym_opt": "s2", "state_opt": "s1"}], "ariths": [{"op": "or", "sym_const": 245, "sym_opt": "const", "state_opt": "s1", "state_const": 192}, {"op": "subr", "sym_const": 15, "sym_opt": "const", "state_opt": "s1", "state_const": 8}]}, {"logic_ops": ["left"], "preds": [{"op": "eq", "const": 67, "sym_opt": "s1", "state_opt": "s1"}], "ariths": [{"op": "and", "sym_const": 8, "sym_opt": "const", "state_opt": "const", "state_const": 72}, {"op": "and", "sym_const": 222, "sym_opt": "const", "state_opt": "const", "state_const": 218}]}, {"logic_ops": ["left"], "preds": [{"op": "ge", "const": 167, "sym_opt": "s2", "state_opt": "s1"}], "ariths": [{"op": "or", "sym_const": 0, "sym_opt": "s2", "state_opt": "s1", "state_const": 179}, {"op": "and", "sym_const": 0, "sym_opt": "s1", "state_opt": "const", "state_const": 245}]}]}