{"bitvecsize": 8, "symbols_1": {"J": 219, "K": 106, "L": 160, "M": 176, "N": 1}, "symbols_2": {"J": 181, "K": 103, "L": 198, "M": 124, "N": 32}, "regact_id": {"J": 1, "K": 0, "L": 0, "M": 0, "N": 2}, "states_1": {"-1_0": 44, "0_0": 0, "1_0": 164, "2_0": 56, "3_0": 132, "4_0": 124, "5_0": 32, "6_0": 216, "7_0": 106, "8_0": 218}, "states_2": {"-1_0": 0, "0_0": 132, "1_0": 156, "2_0": 164, "3_0": 88, "4_0": 180, "5_0": 252, "6_0": 106, "7_0": 250, "8_0": 250}, "regacts": [{"logic_ops": ["or"], "preds": [{"op": "le", "const": 242, "sym_opt": "s1", "state_opt": "s1"}, {"op": "le", "const": 164, "sym_opt": "s2", "state_opt": "s2"}], "ariths": [{"op": "xor", "sym_const": 55, "sym_opt": "const", "state_opt": "const", "state_const": 27}, {"op": "and", "sym_const": 229, "sym_opt": "s2", "state_opt": "const", "state_const": 0}, {"op": "sub", "sym_const": 212, "sym_opt": "const", "state_opt": "s2", "state_const": 173}, {"op": "or", "sym_const": 70, "sym_opt": "s1", "state_opt": "s1", "state_const": 66}]}, {"logic_ops": ["or"], "preds": [{"op": "le", "const": 106, "sym_opt": "const", "state_opt": "s1"}, {"op": "le", "const": 77, "sym_opt": "s1", "state_opt": "s1"}], "ariths": [{"op": "plus", "sym_const": 48, "sym_opt": "const", "state_opt": "const", "state_const": 252}, {"op": "and", "sym_const": 122, "sym_opt": "const", "state_opt": "const", "state_const": 5}, {"op": "xor", "sym_const": 32, "sym_opt": "const", "state_opt": "s2", "state_const": 112}, {"op": "or", "sym_const": 24, "sym_opt": "const", "state_opt": "s2", "state_const": 109}]}, {"logic_ops": ["and"], "preds": [{"op": "neq", "const": 92, "sym_opt": "const", "state_opt": "s2"}, {"op": "neq", "const": 37, "sym_opt": "s1", "state_opt": "s1"}], "ariths": [{"op": "sub", "sym_const": 192, "sym_opt": "const", "state_opt": "const", "state_const": 148}, {"op": "and", "sym_const": 254, "sym_opt": "s1", "state_opt": "s1", "state_const": 128}, {"op": "plus", "sym_const": 224, "sym_opt": "const", "state_opt": "s2", "state_const": 81}, {"op": "plus", "sym_const": 21, "sym_opt": "s2", "state_opt": "s1", "state_const": 5}]}]}