{"bitvecsize": 8, "symbols_1": {"H": 61, "I": 77, "J": 158}, "symbols_2": {"H": 75, "I": 112, "J": 52}, "regact_id": {"H": 1, "I": 0, "J": 2}, "states_1": {"-1_0": 154, "0_0": 0, "1_0": 255, "2_0": 223, "3_0": 155, "4_0": 158, "5_0": 142, "6_0": 159, "7_0": 235, "8_0": 170}, "states_2": {"-1_0": 32, "0_0": 115, "1_0": 208, "2_0": 45, "3_0": 20, "4_0": 4, "5_0": 4, "6_0": 97, "7_0": 96, "8_0": 32}, "regacts": [{"logic_ops": ["and"], "preds": [{"op": "ge", "const": 64, "sym_opt": "s2", "state_opt": "s1"}, {"op": "ge", "const": 245, "sym_opt": "s2", "state_opt": "s1"}], "ariths": [{"op": "plus", "sym_const": 138, "sym_opt": "const", "state_opt": "s2", "state_const": 168}, {"op": "and", "sym_const": 110, "sym_opt": "const", "state_opt": "s2", "state_const": 159}, {"op": "plus", "sym_const": 0, "sym_opt": "s1", "state_opt": "const", "state_const": 77}, {"op": "sub", "sym_const": 0, "sym_opt": "s1", "state_opt": "const", "state_const": 45}]}, {"logic_ops": ["and"], "preds": [{"op": "le", "const": 230, "sym_opt": "const", "state_opt": "s1"}, {"op": "le", "const": 81, "sym_opt": "s1", "state_opt": "s2"}], "ariths": [{"op": "and", "sym_const": 186, "sym_opt": "const", "state_opt": "s1", "state_const": 58}, {"op": "plus", "sym_const": 74, "sym_opt": "const", "state_opt": "const", "state_const": 214}, {"op": "or", "sym_const": 159, "sym_opt": "const", "state_opt": "s2", "state_const": 83}, {"op": "plus", "sym_const": 93, "sym_opt": "const", "state_opt": "s2", "state_const": 29}]}, {"logic_ops": ["or"], "preds": [{"op": "le", "const": 195, "sym_opt": "s1", "state_opt": "s1"}, {"op": "le", "const": 32, "sym_opt": "const", "state_opt": "s2"}], "ariths": [{"op": "sub", "sym_const": 180, "sym_opt": "const", "state_opt": "const", "state_const": 26}, {"op": "subr", "sym_const": 194, "sym_opt": "const", "state_opt": "const", "state_const": 226}, {"op": "and", "sym_const": 187, "sym_opt": "const", "state_opt": "s1", "state_const": 254}, {"op": "and", "sym_const": 244, "sym_opt": "s2", "state_opt": "s1", "state_const": 42}]}]}