{"bitvecsize": 8, "symbols_1": {"D": 164, "F": 66, "L": 70, "N": 43, "O": 191}, "symbols_2": {"D": 110, "F": 1, "L": 8, "N": 233, "O": 31}, "regact_id": {"D": 2, "F": 0, "L": 0, "N": 2, "O": 0}, "states_1": {"rej_0": 111, "accLOOONO_0": 127, "accFFFFFD_0": 239, "p_0": 0, "pL_0": 8, "pF_0": 1, "pFF_0": 2, "pLO_0": 39, "pFFF_0": 3, "pLOO_0": 70, "pFFFF_0": 4, "pLOOO_0": 101, "pLOOON_0": 96, "pFFFFF_0": 5}, "regacts": [{"logic_ops": ["or"], "preds": [{"op": "le", "const": 0, "sym_opt": "s2", "state_opt": "s1"}, {"op": "ge", "const": 185, "sym_opt": "s1", "state_opt": "s1"}], "ariths": [{"op": "or", "sym_const": 111, "sym_opt": "const", "state_opt": "s1", "state_const": 128}, {"op": "plus", "sym_const": 200, "sym_opt": "s2", "state_opt": "s1", "state_const": 185}]}, {"logic_ops": ["or"], "preds": [{"op": "le", "const": 185, "sym_opt": "s1", "state_opt": "s1"}, {"op": "ge", "const": 148, "sym_opt": "const", "state_opt": "s1"}], "ariths": [{"op": "and", "sym_const": 68, "sym_opt": "s2", "state_opt": "s1", "state_const": 230}, {"op": "xor", "sym_const": 146, "sym_opt": "const", "state_opt": "const", "state_const": 104}]}, {"logic_ops": ["and"], "preds": [{"op": "neq", "const": 87, "sym_opt": "s1", "state_opt": "s1"}, {"op": "neq", "const": 178, "sym_opt": "s2", "state_opt": "s1"}], "ariths": [{"op": "or", "sym_const": 111, "sym_opt": "const", "state_opt": "s1", "state_const": 112}, {"op": "xor", "sym_const": 60, "sym_opt": "s1", "state_opt": "const", "state_const": 75}]}]}