{"bitvecsize": 8, "symbols_1": {"D": 255, "E": 251, "F": 3, "G": 231, "I": 176, "J": 245, "K": 171, "L": 22, "M": 204, "N": 206, "P": 239}, "symbols_2": {"D": 242, "E": 244, "F": 255, "G": 239, "I": 245, "J": 18, "K": 204, "L": 28, "M": 212, "N": 22, "P": 167}, "regact_id": {"D": 1, "E": 2, "F": 2, "G": 2, "I": 0, "J": 2, "K": 2, "L": 2, "M": 2, "N": 2, "P": 1}, "states_1": {"rej_0": 247, "accDDDIPP_0": 231, "accDDFGEE_0": 255, "accJLNMLK_0": 215, "p_0": 0, "pD_0": 54, "pJ_0": 220, "pJL_0": 39, "pDD_0": 242, "pDDD_0": 246, "pJLN_0": 36, "pDDF_0": 9, "pDDDI_0": 243, "pDDFG_0": 250, "pJLNM_0": 223, "pDDFGE_0": 4, "pDDDIP_0": 103, "pJLNML_0": 44}, "states_2": {"rej_0": 247, "accDDDIPP_0": 231, "accDDFGEE_0": 255, "accJLNMLK_0": 215, "p_0": 54, "pD_0": 242, "pJ_0": 245, "pJL_0": 242, "pDD_0": 246, "pDDD_0": 242, "pJLN_0": 245, "pDDF_0": 245, "pDDDI_0": 119, "pDDFG_0": 240, "pJLNM_0": 240, "pDDFGE_0": 245, "pDDDIP_0": 247, "pJLNML_0": 245}, "regacts": [{"logic_ops": ["or"], "preds": [{"op": "eq", "const": 15, "sym_opt": "s2", "state_opt": "s1"}, {"op": "eq", "const": 21, "sym_opt": "s2", "state_opt": "s1"}], "ariths": [{"op": "or", "sym_const": 243, "sym_opt": "const", "state_opt": "s2", "state_const": 16}, {"op": "plus", "sym_const": 0, "sym_opt": "s1", "state_opt": "const", "state_const": 199}, {"op": "or", "sym_const": 199, "sym_opt": "const", "state_opt": "s2", "state_const": 60}, {"op": "or", "sym_const": 199, "sym_opt": "const", "state_opt": "s2", "state_const": 18}]}, {"logic_ops": ["and"], "preds": [{"op": "le", "const": 204, "sym_opt": "s1", "state_opt": "s1"}, {"op": "ge", "const": 152, "sym_opt": "s2", "state_opt": "s2"}], "ariths": [{"op": "or", "sym_const": 199, "sym_opt": "const", "state_opt": "s2", "state_const": 127}, {"op": "or", "sym_const": 199, "sym_opt": "const", "state_opt": "s2", "state_const": 255}, {"op": "and", "sym_const": 0, "sym_opt": "s1", "state_opt": "s2", "state_const": 118}, {"op": "or", "sym_const": 0, "sym_opt": "s2", "state_opt": "s1", "state_const": 244}]}, {"logic_ops": ["and"], "preds": [{"op": "neq", "const": 8, "sym_opt": "s2", "state_opt": "s1"}, {"op": "neq", "const": 11, "sym_opt": "s1", "state_opt": "s1"}], "ariths": [{"op": "or", "sym_const": 199, "sym_opt": "const", "state_opt": "s2", "state_const": 191}, {"op": "or", "sym_const": 199, "sym_opt": "const", "state_opt": "s2", "state_const": 173}, {"op": "sub", "sym_const": 0, "sym_opt": "s2", "state_opt": "s2", "state_const": 56}, {"op": "plus", "sym_const": 0, "sym_opt": "s1", "state_opt": "s1", "state_const": 87}]}]}