{"bitvecsize": 8, "symbols_1": {"I": 234, "J": 255, "K": 107, "L": 147, "M": 220}, "symbols_2": {"I": 0, "J": 243, "K": 128, "L": 109, "M": 83}, "regact_id": {"I": 3, "J": 1, "K": 3, "L": 0, "M": 0}, "states_1": {"rej_0": 51, "accLMLM_0": 32, "accJIKK_0": 68, "p_0": 0, "pJ_0": 60, "pL_0": 136, "pLM_0": 16, "pJI_0": 42, "pLML_0": 152, "pJIK_0": 171}, "states_2": {"rej_0": 192, "accLMLM_0": 211, "accJIKK_0": 183, "p_0": 192, "pJ_0": 192, "pL_0": 192, "pLM_0": 192, "pJI_0": 192, "pLML_0": 192, "pJIK_0": 183}, "regacts": [{"logic_ops": ["left", "and"], "preds": [{"op": "le", "const": 78, "sym_opt": "s1", "state_opt": "s1"}, {"op": "le", "const": 157, "sym_opt": "s2", "state_opt": "s1"}], "ariths": [{"op": "subr", "sym_const": 120, "sym_opt": "const", "state_opt": "s1", "state_const": 208}, {"op": "sub", "sym_const": 107, "sym_opt": "const", "state_opt": "s1", "state_const": 202}, {"op": "xor", "sym_const": 243, "sym_opt": "const", "state_opt": "s2", "state_const": 173}, {"op": "plus", "sym_const": 0, "sym_opt": "const", "state_opt": "s2", "state_const": 100}]}, {"logic_ops": ["or", "left"], "preds": [{"op": "ge", "const": 226, "sym_opt": "s1", "state_opt": "s1"}, {"op": "eq", "const": 240, "sym_opt": "const", "state_opt": "s1"}], "ariths": [{"op": "xor", "sym_const": 78, "sym_opt": "s2", "state_opt": "s2", "state_const": 179}, {"op": "and", "sym_const": 247, "sym_opt": "const", "state_opt": "s2", "state_const": 247}, {"op": "plus", "sym_const": 124, "sym_opt": "const", "state_opt": "s2", "state_const": 74}, {"op": "sub", "sym_const": 215, "sym_opt": "const", "state_opt": "const", "state_const": 23}]}, {"logic_ops": ["right", "left"], "preds": [{"op": "neq", "const": 0, "sym_opt": "const", "state_opt": "const"}, {"op": "le", "const": 130, "sym_opt": "s2", "state_opt": "s1"}], "ariths": [{"op": "xor", "sym_const": 115, "sym_opt": "s2", "state_opt": "s2", "state_const": 32}, {"op": "xor", "sym_const": 57, "sym_opt": "const", "state_opt": "const", "state_const": 249}, {"op": "plus", "sym_const": 124, "sym_opt": "const", "state_opt": "s2", "state_const": 176}, {"op": "and", "sym_const": 247, "sym_opt": "const", "state_opt": "s2", "state_const": 160}]}, {"logic_ops": ["or", "right"], "preds": [{"op": "eq", "const": 218, "sym_opt": "s1", "state_opt": "s1"}, {"op": "eq", "const": 107, "sym_opt": "s1", "state_opt": "s1"}], "ariths": [{"op": "sub", "sym_const": 208, "sym_opt": "s1", "state_opt": "s2", "state_const": 248}, {"op": "sub", "sym_const": 119, "sym_opt": "const", "state_opt": "s2", "state_const": 45}, {"op": "xor", "sym_const": 243, "sym_opt": "const", "state_opt": "s2", "state_const": 165}, {"op": "or", "sym_const": 39, "sym_opt": "s2", "state_opt": "s2", "state_const": 254}]}]}