{"bitvecsize": 8, "symbols_1": {"B": 32, "C": 177, "F": 172, "G": 254}, "symbols_2": {"B": 160, "C": 191, "F": 144, "G": 45}, "regact_id": {"B": 3, "C": 0, "F": 2, "G": 3}, "states_1": {"rej_0": 222, "accCBFF_0": 254, "accFFGG_0": 134, "p_0": 0, "pC_0": 190, "pF_0": 112, "pCB_0": 30, "pFF_0": 224, "pCBF_0": 142, "pFFG_0": 179}, "states_2": {"rej_0": 103, "accCBFF_0": 135, "accFFGG_0": 15, "p_0": 103, "pC_0": 103, "pF_0": 103, "pCB_0": 103, "pFF_0": 103, "pCBF_0": 103, "pFFG_0": 103}, "regacts": [{"logic_ops": ["or", "and"], "preds": [{"op": "eq", "const": 129, "sym_opt": "s1", "state_opt": "s1"}, {"op": "neq", "const": 65, "sym_opt": "s2", "state_opt": "s1"}], "ariths": [{"op": "plus", "sym_const": 119, "sym_opt": "const", "state_opt": "s2", "state_const": 86}, {"op": "xor", "sym_const": 238, "sym_opt": "s1", "state_opt": "const", "state_const": 74}, {"op": "sub", "sym_const": 103, "sym_opt": "const", "state_opt": "const", "state_const": 169}, {"op": "and", "sym_const": 255, "sym_opt": "const", "state_opt": "s2", "state_const": 119}]}, {"logic_ops": ["or", "and"], "preds": [{"op": "ge", "const": 162, "sym_opt": "s2", "state_opt": "const"}, {"op": "le", "const": 67, "sym_opt": "const", "state_opt": "const"}], "ariths": [{"op": "subr", "sym_const": 173, "sym_opt": "const", "state_opt": "s1", "state_const": 148}, {"op": "sub", "sym_const": 180, "sym_opt": "const", "state_opt": "const", "state_const": 51}, {"op": "plus", "sym_const": 55, "sym_opt": "const", "state_opt": "s2", "state_const": 167}, {"op": "sub", "sym_const": 85, "sym_opt": "const", "state_opt": "const", "state_const": 46}]}, {"logic_ops": ["and", "right"], "preds": [{"op": "le", "const": 86, "sym_opt": "s1", "state_opt": "s1"}, {"op": "neq", "const": 198, "sym_opt": "s1", "state_opt": "s1"}], "ariths": [{"op": "subr", "sym_const": 137, "sym_opt": "const", "state_opt": "s2", "state_const": 242}, {"op": "or", "sym_const": 5, "sym_opt": "const", "state_opt": "s2", "state_const": 47}, {"op": "subr", "sym_const": 144, "sym_opt": "s2", "state_opt": "s1", "state_const": 108}, {"op": "xor", "sym_const": 6, "sym_opt": "const", "state_opt": "const", "state_const": 129}]}, {"logic_ops": ["and", "left"], "preds": [{"op": "neq", "const": 32, "sym_opt": "s2", "state_opt": "s1"}, {"op": "neq", "const": 34, "sym_opt": "s1", "state_opt": "s1"}], "ariths": [{"op": "plus", "sym_const": 119, "sym_opt": "const", "state_opt": "s2", "state_const": 122}, {"op": "plus", "sym_const": 0, "sym_opt": "const", "state_opt": "s2", "state_const": 241}, {"op": "subr", "sym_const": 137, "sym_opt": "s2", "state_opt": "s1", "state_const": 174}, {"op": "sub", "sym_const": 188, "sym_opt": "s2", "state_opt": "const", "state_const": 30}]}]}