{"bitvecsize": 8, "symbols_1": {"K": 100, "L": 72}, "symbols_2": {"K": 63, "L": 28}, "regact_id": {"K": 3, "L": 1}, "states_1": {"-1_0": 238, "0_0": 0, "1_0": 130, "2_0": 102, "3_0": 74, "4_0": 46, "5_0": 174, "6_0": 146, "7_0": 118, "8_0": 90, "9_0": 62, "10_0": 254}, "regacts": [{"logic_ops": ["left"], "preds": [{"op": "eq", "const": 146, "sym_opt": "s1", "state_opt": "s1"}], "ariths": [{"op": "subr", "sym_const": 106, "sym_opt": "const", "state_opt": "const", "state_const": 103}, {"op": "or", "sym_const": 42, "sym_opt": "const", "state_opt": "const", "state_const": 102}]}, {"logic_ops": ["left"], "preds": [{"op": "ge", "const": 121, "sym_opt": "s1", "state_opt": "s1"}], "ariths": [{"op": "subr", "sym_const": 0, "sym_opt": "s2", "state_opt": "s1", "state_const": 129}, {"op": "or", "sym_const": 238, "sym_opt": "const", "state_opt": "s1", "state_const": 5}]}, {"logic_ops": ["left"], "preds": [{"op": "le", "const": 140, "sym_opt": "s1", "state_opt": "const"}], "ariths": [{"op": "sub", "sym_const": 60, "sym_opt": "const", "state_opt": "const", "state_const": 66}, {"op": "or", "sym_const": 73, "sym_opt": "const", "state_opt": "const", "state_const": 103}]}, {"logic_ops": ["left"], "preds": [{"op": "ge", "const": 209, "sym_opt": "const", "state_opt": "s1"}], "ariths": [{"op": "or", "sym_const": 236, "sym_opt": "const", "state_opt": "const", "state_const": 6}, {"op": "or", "sym_const": 130, "sym_opt": "const", "state_opt": "s1", "state_const": 126}]}]}