{"bitvecsize": 8, "symbols_1": {"G": 132, "H": 14, "I": 26, "J": 206, "L": 159, "M": 254, "N": 248}, "symbols_2": {"G": 69, "H": 5, "I": 85, "J": 197, "L": 65, "M": 131, "N": 196}, "regact_id": {"G": 1, "H": 3, "I": 0, "J": 3, "L": 3, "M": 1, "N": 2}, "states_1": {"rej_0": 222, "accNNNMML_0": 255, "accIJIGHJ_0": 254, "p_0": 0, "pI_0": 26, "pN_0": 196, "pNN_0": 214, "pIJ_0": 76, "pNNN_0": 154, "pIJI_0": 94, "pNNNM_0": 156, "pIJIG_0": 218, "pNNNMM_0": 158, "pIJIGH_0": 204}, "regacts": [{"logic_ops": ["or"], "preds": [{"op": "le", "const": 9, "sym_opt": "s1", "state_opt": "s1"}, {"op": "eq", "const": 204, "sym_opt": "s1", "state_opt": "s1"}], "ariths": [{"op": "sub", "sym_const": 253, "sym_opt": "s2", "state_opt": "const", "state_const": 119}, {"op": "or", "sym_const": 254, "sym_opt": "s1", "state_opt": "s1", "state_const": 16}]}, {"logic_ops": ["or"], "preds": [{"op": "ge", "const": 27, "sym_opt": "s1", "state_opt": "s1"}, {"op": "ge", "const": 223, "sym_opt": "s2", "state_opt": "s1"}], "ariths": [{"op": "or", "sym_const": 222, "sym_opt": "const", "state_opt": "s1", "state_const": 142}, {"op": "subr", "sym_const": 221, "sym_opt": "s1", "state_opt": "s1", "state_const": 226}]}, {"logic_ops": ["or"], "preds": [{"op": "eq", "const": 50, "sym_opt": "s1", "state_opt": "s1"}, {"op": "eq", "const": 0, "sym_opt": "const", "state_opt": "s1"}], "ariths": [{"op": "plus", "sym_const": 196, "sym_opt": "s2", "state_opt": "s1", "state_const": 212}, {"op": "or", "sym_const": 214, "sym_opt": "const", "state_opt": "s1", "state_const": 180}]}, {"logic_ops": ["or"], "preds": [{"op": "eq", "const": 33, "sym_opt": "s2", "state_opt": "s1"}, {"op": "eq", "const": 102, "sym_opt": "s1", "state_opt": "s1"}], "ariths": [{"op": "subr", "sym_const": 202, "sym_opt": "s1", "state_opt": "s1", "state_const": 158}, {"op": "or", "sym_const": 222, "sym_opt": "const", "state_opt": "s1", "state_const": 129}]}]}