{"bitvecsize": 8, "symbols_1": {"K": 131, "L": 132, "M": 233, "N": 57}, "symbols_2": {"K": 103, "L": 175, "M": 20, "N": 132}, "regact_id": {"K": 2, "L": 0, "M": 3, "N": 1}, "states_1": {"rej_0": 197, "accNKNNNM_0": 215, "accMKLKKK_0": 220, "p_0": 0, "pM_0": 73, "pN_0": 65, "pMK_0": 144, "pNK_0": 136, "pNKN_0": 139, "pMKL_0": 7, "pNKNN_0": 142, "pMKLK_0": 78, "pNKNNN_0": 145, "pMKLKK_0": 149}, "states_2": {"rej_0": 65, "accNKNNNM_0": 83, "accMKLKKK_0": 88, "p_0": 197, "pM_0": 65, "pN_0": 65, "pMK_0": 65, "pNK_0": 65, "pNKN_0": 65, "pMKL_0": 65, "pNKNN_0": 65, "pMKLK_0": 65, "pNKNNN_0": 65, "pMKLKK_0": 65}, "regacts": [{"logic_ops": ["or", "and"], "preds": [{"op": "neq", "const": 0, "sym_opt": "const", "state_opt": "const"}, {"op": "neq", "const": 112, "sym_opt": "const", "state_opt": "s1"}], "ariths": [{"op": "or", "sym_const": 4, "sym_opt": "s1", "state_opt": "s2", "state_const": 1}, {"op": "and", "sym_const": 106, "sym_opt": "const", "state_opt": "s2", "state_const": 110}, {"op": "subr", "sym_const": 3, "sym_opt": "const", "state_opt": "const", "state_const": 10}, {"op": "and", "sym_const": 123, "sym_opt": "const", "state_opt": "s2", "state_const": 75}]}, {"logic_ops": ["and", "right"], "preds": [{"op": "le", "const": 48, "sym_opt": "const", "state_opt": "s1"}, {"op": "le", "const": 56, "sym_opt": "s1", "state_opt": "s1"}], "ariths": [{"op": "plus", "sym_const": 3, "sym_opt": "const", "state_opt": "s1", "state_const": 25}, {"op": "xor", "sym_const": 6, "sym_opt": "s1", "state_opt": "const", "state_const": 120}, {"op": "xor", "sym_const": 207, "sym_opt": "s2", "state_opt": "s2", "state_const": 64}, {"op": "and", "sym_const": 91, "sym_opt": "const", "state_opt": "s2", "state_const": 131}]}, {"logic_ops": ["or", "right"], "preds": [{"op": "ge", "const": 149, "sym_opt": "s2", "state_opt": "s1"}, {"op": "eq", "const": 232, "sym_opt": "s1", "state_opt": "s1"}], "ariths": [{"op": "plus", "sym_const": 71, "sym_opt": "const", "state_opt": "s1", "state_const": 2}, {"op": "sub", "sym_const": 153, "sym_opt": "const", "state_opt": "s2", "state_const": 47}, {"op": "or", "sym_const": 132, "sym_opt": "const", "state_opt": "s2", "state_const": 64}, {"op": "and", "sym_const": 91, "sym_opt": "const", "state_opt": "s2", "state_const": 58}]}, {"logic_ops": ["left", "or"], "preds": [{"op": "eq", "const": 91, "sym_opt": "s2", "state_opt": "s1"}, {"op": "eq", "const": 173, "sym_opt": "const", "state_opt": "s2"}], "ariths": [{"op": "sub", "sym_const": 242, "sym_opt": "const", "state_opt": "const", "state_const": 27}, {"op": "or", "sym_const": 19, "sym_opt": "const", "state_opt": "s2", "state_const": 248}, {"op": "plus", "sym_const": 132, "sym_opt": "const", "state_opt": "s2", "state_const": 22}, {"op": "and", "sym_const": 121, "sym_opt": "const", "state_opt": "s2", "state_const": 211}]}]}