{"bitvecsize": 8, "symbols_1": {"I": 131, "J": 1, "K": 137, "L": 255, "M": 95}, "symbols_2": {"I": 249, "J": 221, "K": 252, "L": 248, "M": 197}, "regact_id": {"I": 2, "J": 1, "K": 2, "L": 0, "M": 1}, "states_1": {"rej_0": 95, "accLMLMMLLL_0": 127, "accJIKKKKKK_0": 255, "p_0": 0, "pJ_0": 30, "pL_0": 1, "pJI_0": 23, "pLM_0": 5, "pJIK_0": 19, "pLML_0": 6, "pJIKK_0": 15, "pLMLM_0": 83, "pJIKKK_0": 11, "pLMLMM_0": 24, "pLMLMML_0": 25, "pJIKKKK_0": 7, "pJIKKKKK_0": 3, "pLMLMMLL_0": 26}, "states_2": {"rej_0": 95, "accLMLMMLLL_0": 127, "accJIKKKKKK_0": 255, "p_0": 227, "pJ_0": 6, "pL_0": 90, "pJI_0": 5, "pLM_0": 149, "pJIK_0": 4, "pLML_0": 12, "pJIKK_0": 3, "pLMLM_0": 71, "pJIKKK_0": 2, "pLMLMM_0": 130, "pLMLMML_0": 249, "pJIKKKK_0": 1, "pJIKKKKK_0": 0, "pLMLMMLL_0": 112}, "regacts": [{"logic_ops": ["and"], "preds": [{"op": "le", "const": 230, "sym_opt": "const", "state_opt": "s1"}, {"op": "le", "const": 7, "sym_opt": "s1", "state_opt": "s2"}], "ariths": [{"op": "subr", "sym_const": 255, "sym_opt": "s1", "state_opt": "s1", "state_const": 96}, {"op": "subr", "sym_const": 137, "sym_opt": "const", "state_opt": "s2", "state_const": 206}, {"op": "or", "sym_const": 95, "sym_opt": "const", "state_opt": "s2", "state_const": 140}, {"op": "or", "sym_const": 95, "sym_opt": "const", "state_opt": "s2", "state_const": 171}]}, {"logic_ops": ["or"], "preds": [{"op": "le", "const": 155, "sym_opt": "s1", "state_opt": "s2"}, {"op": "le", "const": 36, "sym_opt": "const", "state_opt": "s2"}], "ariths": [{"op": "or", "sym_const": 95, "sym_opt": "const", "state_opt": "s1", "state_const": 65}, {"op": "or", "sym_const": 95, "sym_opt": "const", "state_opt": "s1", "state_const": 114}, {"op": "sub", "sym_const": 95, "sym_opt": "s1", "state_opt": "s2", "state_const": 70}, {"op": "subr", "sym_const": 112, "sym_opt": "s2", "state_opt": "s2", "state_const": 49}]}, {"logic_ops": ["or"], "preds": [{"op": "ge", "const": 247, "sym_opt": "s1", "state_opt": "s2"}, {"op": "ge", "const": 113, "sym_opt": "s1", "state_opt": "s2"}], "ariths": [{"op": "or", "sym_const": 95, "sym_opt": "const", "state_opt": "s1", "state_const": 96}, {"op": "or", "sym_const": 95, "sym_opt": "const", "state_opt": "s1", "state_const": 28}, {"op": "plus", "sym_const": 49, "sym_opt": "s2", "state_opt": "s1", "state_const": 52}, {"op": "plus", "sym_const": 255, "sym_opt": "const", "state_opt": "s2", "state_const": 206}]}]}