{"bitvecsize": 8, "symbols_1": {"I": 252, "J": 206, "K": 141, "M": 193, "N": 58}, "symbols_2": {"I": 241, "J": 129, "K": 21, "M": 248, "N": 103}, "regact_id": {"I": 1, "J": 2, "K": 2, "M": 1, "N": 1}, "states_1": {"rej_0": 205, "accMKNN_0": 255, "accIKKJ_0": 223, "accJJKK_0": 253, "p_0": 0, "pM_0": 140, "pI_0": 133, "pJ_0": 13, "pJJ_0": 129, "pIK_0": 141, "pMK_0": 200, "pMKN_0": 197, "pIKK_0": 1, "pJJK_0": 137}, "states_2": {"rej_0": 162, "accMKNN_0": 162, "accIKKJ_0": 162, "accJJKK_0": 162, "p_0": 116, "pM_0": 77, "pI_0": 136, "pJ_0": 0, "pJJ_0": 140, "pIK_0": 20, "pMK_0": 162, "pMKN_0": 152, "pIKK_0": 162, "pJJK_0": 24}, "regacts": [{"logic_ops": ["left", "left"], "preds": [{"op": "ge", "const": 74, "sym_opt": "s2", "state_opt": "const"}, {"op": "neq", "const": 15, "sym_opt": "s2", "state_opt": "const"}], "ariths": [{"op": "subr", "sym_const": 128, "sym_opt": "const", "state_opt": "const", "state_const": 61}, {"op": "plus", "sym_const": 75, "sym_opt": "const", "state_opt": "const", "state_const": 89}, {"op": "or", "sym_const": 143, "sym_opt": "const", "state_opt": "const", "state_const": 77}, {"op": "plus", "sym_const": 26, "sym_opt": "const", "state_opt": "const", "state_const": 138}]}, {"logic_ops": ["or", "or"], "preds": [{"op": "le", "const": 5, "sym_opt": "s2", "state_opt": "s2"}, {"op": "le", "const": 76, "sym_opt": "s2", "state_opt": "s1"}], "ariths": [{"op": "or", "sym_const": 205, "sym_opt": "const", "state_opt": "s1", "state_const": 197}, {"op": "plus", "sym_const": 203, "sym_opt": "const", "state_opt": "const", "state_const": 215}, {"op": "xor", "sym_const": 178, "sym_opt": "s2", "state_opt": "s2", "state_const": 207}, {"op": "sub", "sym_const": 125, "sym_opt": "s1", "state_opt": "s2", "state_const": 248}]}, {"logic_ops": ["left", "or"], "preds": [{"op": "ge", "const": 178, "sym_opt": "s1", "state_opt": "s1"}, {"op": "le", "const": 130, "sym_opt": "s2", "state_opt": "s2"}], "ariths": [{"op": "or", "sym_const": 205, "sym_opt": "const", "state_opt": "s1", "state_const": 72}, {"op": "or", "sym_const": 162, "sym_opt": "const", "state_opt": "const", "state_const": 0}, {"op": "sub", "sym_const": 48, "sym_opt": "s2", "state_opt": "s2", "state_const": 64}, {"op": "plus", "sym_const": 140, "sym_opt": "const", "state_opt": "s2", "state_const": 27}]}]}