{"bitvecsize": 8, "symbols_1": {"G": 236, "H": 184, "I": 153, "K": 196, "L": 254, "N": 221, "O": 209}, "symbols_2": {"G": 25, "H": 45, "I": 201, "K": 10, "L": 198, "N": 72, "O": 248}, "regact_id": {"G": 0, "H": 3, "I": 3, "K": 0, "L": 0, "N": 0, "O": 3}, "states_1": {"rej_0": 236, "accLKON_0": 76, "accGHIG_0": 44, "p_0": 0, "pL_0": 215, "pG_0": 42, "pGH_0": 73, "pLK_0": 12, "pLKO_0": 126, "pGHI_0": 173}, "states_2": {"rej_0": 255, "accLKON_0": 95, "accGHIG_0": 63, "p_0": 239, "pL_0": 254, "pG_0": 236, "pGH_0": 237, "pLK_0": 237, "pLKO_0": 252, "pGHI_0": 237}, "regacts": [{"logic_ops": ["or"], "preds": [{"op": "eq", "const": 248, "sym_opt": "s2", "state_opt": "s2"}, {"op": "eq", "const": 58, "sym_opt": "s2", "state_opt": "s1"}], "ariths": [{"op": "sub", "sym_const": 94, "sym_opt": "s2", "state_opt": "s2", "state_const": 210}, {"op": "sub", "sym_const": 135, "sym_opt": "s1", "state_opt": "s1", "state_const": 45}, {"op": "and", "sym_const": 236, "sym_opt": "const", "state_opt": "s2", "state_const": 207}, {"op": "or", "sym_const": 23, "sym_opt": "const", "state_opt": "s2", "state_const": 249}]}, {"logic_ops": ["and"], "preds": [{"op": "ge", "const": 200, "sym_opt": "const", "state_opt": "const"}, {"op": "ge", "const": 60, "sym_opt": "s2", "state_opt": "s1"}], "ariths": [{"op": "subr", "sym_const": 192, "sym_opt": "const", "state_opt": "s1", "state_const": 119}, {"op": "subr", "sym_const": 225, "sym_opt": "const", "state_opt": "const", "state_const": 160}, {"op": "plus", "sym_const": 211, "sym_opt": "const", "state_opt": "s2", "state_const": 208}, {"op": "sub", "sym_const": 98, "sym_opt": "const", "state_opt": "const", "state_const": 107}]}, {"logic_ops": ["or"], "preds": [{"op": "eq", "const": 191, "sym_opt": "s1", "state_opt": "s1"}, {"op": "ge", "const": 118, "sym_opt": "s2", "state_opt": "s2"}], "ariths": [{"op": "subr", "sym_const": 74, "sym_opt": "s1", "state_opt": "s2", "state_const": 249}, {"op": "and", "sym_const": 104, "sym_opt": "const", "state_opt": "const", "state_const": 135}, {"op": "sub", "sym_const": 131, "sym_opt": "const", "state_opt": "const", "state_const": 175}, {"op": "subr", "sym_const": 250, "sym_opt": "const", "state_opt": "const", "state_const": 16}]}, {"logic_ops": ["or"], "preds": [{"op": "ge", "const": 29, "sym_opt": "s1", "state_opt": "s1"}, {"op": "le", "const": 38, "sym_opt": "s1", "state_opt": "s1"}], "ariths": [{"op": "and", "sym_const": 236, "sym_opt": "const", "state_opt": "s2", "state_const": 213}, {"op": "or", "sym_const": 31, "sym_opt": "const", "state_opt": "s2", "state_const": 152}, {"op": "subr", "sym_const": 95, "sym_opt": "s2", "state_opt": "const", "state_const": 118}, {"op": "or", "sym_const": 50, "sym_opt": "s2", "state_opt": "const", "state_const": 228}]}]}