{"bitvecsize": 8, "symbols_1": {"J": 245, "K": 96, "L": 136, "N": 32, "O": 101}, "symbols_2": {"J": 64, "K": 20, "L": 29, "N": 156, "O": 112}, "regact_id": {"J": 1, "K": 3, "L": 0, "N": 0, "O": 1}, "states_1": {"-1_0": 250, "0_0": 0, "1_0": 88, "2_0": 208, "3_0": 176, "4_0": 144, "5_0": 112, "6_0": 80, "7_0": 200, "8_0": 168, "9_0": 136, "10_0": 104, "11_0": 224, "12_0": 254}, "regacts": [{"logic_ops": ["and"], "preds": [{"op": "le", "const": 40, "sym_opt": "const", "state_opt": "s1"}, {"op": "le", "const": 123, "sym_opt": "s2", "state_opt": "s1"}], "ariths": [{"op": "subr", "sym_const": 130, "sym_opt": "s1", "state_opt": "s1", "state_const": 92}, {"op": "or", "sym_const": 250, "sym_opt": "const", "state_opt": "s1", "state_const": 82}]}, {"logic_ops": ["and"], "preds": [{"op": "le", "const": 11, "sym_opt": "s1", "state_opt": "s1"}, {"op": "le", "const": 64, "sym_opt": "s2", "state_opt": "s1"}], "ariths": [{"op": "plus", "sym_const": 41, "sym_opt": "s1", "state_opt": "const", "state_const": 99}, {"op": "or", "sym_const": 250, "sym_opt": "const", "state_opt": "s1", "state_const": 128}]}, {"logic_ops": ["left"], "preds": [{"op": "ge", "const": 144, "sym_opt": "const", "state_opt": "s1"}, {"op": "le", "const": 153, "sym_opt": "s2", "state_opt": "const"}], "ariths": [{"op": "plus", "sym_const": 104, "sym_opt": "const", "state_opt": "s1", "state_const": 204}, {"op": "or", "sym_const": 10, "sym_opt": "const", "state_opt": "const", "state_const": 82}]}, {"logic_ops": ["or"], "preds": [{"op": "eq", "const": 192, "sym_opt": "s1", "state_opt": "s1"}, {"op": "eq", "const": 162, "sym_opt": "s1", "state_opt": "s1"}], "ariths": [{"op": "sub", "sym_const": 244, "sym_opt": "const", "state_opt": "const", "state_const": 246}, {"op": "or", "sym_const": 178, "sym_opt": "const", "state_opt": "const", "state_const": 120}]}]}