{"bitvecsize": 8, "symbols_1": {"F": 255, "G": 155, "H": 79, "I": 24, "J": 129, "K": 226}, "symbols_2": {"F": 154, "G": 86, "H": 0, "I": 25, "J": 191, "K": 24}, "regact_id": {"F": 2, "G": 2, "H": 2, "I": 1, "J": 3, "K": 2}, "states_1": {"-1_0": 191, "0_0": 0, "1_0": 14, "2_0": 28, "3_0": 27, "4_0": 182, "5_0": 5, "6_0": 19, "7_0": 33, "8_0": 160, "9_0": 31, "10_0": 158, "11_0": 128, "12_0": 255}, "regacts": [{"logic_ops": ["or"], "preds": [{"op": "le", "const": 71, "sym_opt": "s2", "state_opt": "s1"}, {"op": "eq", "const": 18, "sym_opt": "s1", "state_opt": "const"}], "ariths": [{"op": "subr", "sym_const": 65, "sym_opt": "const", "state_opt": "s1", "state_const": 114}, {"op": "sub", "sym_const": 175, "sym_opt": "const", "state_opt": "const", "state_const": 240}]}, {"logic_ops": ["or"], "preds": [{"op": "le", "const": 232, "sym_opt": "s2", "state_opt": "s1"}, {"op": "le", "const": 76, "sym_opt": "s2", "state_opt": "s1"}], "ariths": [{"op": "or", "sym_const": 191, "sym_opt": "const", "state_opt": "s1", "state_const": 255}, {"op": "plus", "sym_const": 14, "sym_opt": "const", "state_opt": "s1", "state_const": 166}]}, {"logic_ops": ["and"], "preds": [{"op": "neq", "const": 74, "sym_opt": "s2", "state_opt": "s1"}, {"op": "neq", "const": 74, "sym_opt": "s1", "state_opt": "s1"}], "ariths": [{"op": "or", "sym_const": 191, "sym_opt": "const", "state_opt": "s1", "state_const": 6}, {"op": "plus", "sym_const": 171, "sym_opt": "s1", "state_opt": "s1", "state_const": 42}]}, {"logic_ops": ["or"], "preds": [{"op": "le", "const": 99, "sym_opt": "const", "state_opt": "s1"}, {"op": "eq", "const": 96, "sym_opt": "const", "state_opt": "s1"}], "ariths": [{"op": "subr", "sym_const": 114, "sym_opt": "s1", "state_opt": "s1", "state_const": 116}, {"op": "or", "sym_const": 139, "sym_opt": "s2", "state_opt": "s1", "state_const": 175}]}]}