{"bitvecsize": 8, "symbols_1": {"L": 226, "M": 16}, "symbols_2": {"L": 5, "M": 125}, "regact_id": {"L": 2, "M": 1}, "states_1": {"-1_0": 125, "0_0": 0, "1_0": 189, "2_0": 170, "3_0": 127, "4_0": 48, "5_0": 255, "6_0": 133, "7_0": 94, "8_0": 253}, "states_2": {"-1_0": 65, "0_0": 1, "1_0": 248, "2_0": 45, "3_0": 98, "4_0": 151, "5_0": 215, "6_0": 12, "7_0": 65, "8_0": 248}, "regacts": [{"logic_ops": ["or"], "preds": [{"op": "ge", "const": 92, "sym_opt": "const", "state_opt": "s2"}, {"op": "le", "const": 126, "sym_opt": "s1", "state_opt": "s1"}], "ariths": [{"op": "plus", "sym_const": 248, "sym_opt": "const", "state_opt": "s2", "state_const": 121}, {"op": "sub", "sym_const": 173, "sym_opt": "const", "state_opt": "const", "state_const": 168}, {"op": "xor", "sym_const": 148, "sym_opt": "const", "state_opt": "s1", "state_const": 10}, {"op": "or", "sym_const": 211, "sym_opt": "const", "state_opt": "const", "state_const": 24}]}, {"logic_ops": ["and"], "preds": [{"op": "neq", "const": 243, "sym_opt": "s1", "state_opt": "s1"}, {"op": "le", "const": 132, "sym_opt": "s2", "state_opt": "s1"}], "ariths": [{"op": "xor", "sym_const": 82, "sym_opt": "const", "state_opt": "s2", "state_const": 50}, {"op": "plus", "sym_const": 53, "sym_opt": "const", "state_opt": "s2", "state_const": 229}, {"op": "or", "sym_const": 0, "sym_opt": "s2", "state_opt": "s2", "state_const": 196}, {"op": "or", "sym_const": 64, "sym_opt": "const", "state_opt": "s2", "state_const": 225}]}, {"logic_ops": ["or"], "preds": [{"op": "le", "const": 27, "sym_opt": "s2", "state_opt": "s1"}, {"op": "le", "const": 70, "sym_opt": "s1", "state_opt": "s2"}], "ariths": [{"op": "sub", "sym_const": 211, "sym_opt": "const", "state_opt": "const", "state_const": 86}, {"op": "sub", "sym_const": 249, "sym_opt": "const", "state_opt": "const", "state_const": 184}, {"op": "or", "sym_const": 189, "sym_opt": "const", "state_opt": "s2", "state_const": 152}, {"op": "and", "sym_const": 254, "sym_opt": "const", "state_opt": "const", "state_const": 249}]}, {"logic_ops": ["or"], "preds": [{"op": "ge", "const": 254, "sym_opt": "s1", "state_opt": "s1"}, {"op": "le", "const": 32, "sym_opt": "const", "state_opt": "s2"}], "ariths": [{"op": "plus", "sym_const": 186, "sym_opt": "const", "state_opt": "const", "state_const": 39}, {"op": "and", "sym_const": 189, "sym_opt": "const", "state_opt": "const", "state_const": 97}, {"op": "plus", "sym_const": 32, "sym_opt": "const", "state_opt": "const", "state_const": 169}, {"op": "or", "sym_const": 45, "sym_opt": "const", "state_opt": "const", "state_const": 134}]}]}